LICENSE.txt
MANIFEST.in
README.rst
setup.py
investmentutility/__init__.py
investmentutility.egg-info/PKG-INFO
investmentutility.egg-info/SOURCES.txt
investmentutility.egg-info/dependency_links.txt
investmentutility.egg-info/requires.txt
investmentutility.egg-info/top_level.txt